{"stats":{"minecraft:custom":{"minecraft:jump":250,"minecraft:open_chest":1,"minecraft:time_since_rest":2113,"minecraft:damage_taken":260,"minecraft:leave_game":5,"minecraft:play_one_minute":8167,"minecraft:crouch_one_cm":968,"minecraft:time_since_death":2073,"minecraft:sprint_one_cm":50735,"minecraft:walk_one_cm":25385,"minecraft:walk_on_water_one_cm":261,"minecraft:deaths":1,"minecraft:sneak_time":175,"minecraft:fall_one_cm":8784,"minecraft:fly_one_cm":43867},"minecraft:mined":{"minecraft:spruce_leaves":6}},"DataVersion":1976}